pytest_testlink_adaptor.py
pytest_testlink_adaptor-0.33.dist-info/LICENSE
pytest_testlink_adaptor-0.33.dist-info/METADATA
pytest_testlink_adaptor-0.33.dist-info/WHEEL
pytest_testlink_adaptor-0.33.dist-info/entry_points.txt
pytest_testlink_adaptor-0.33.dist-info/top_level.txt
pytest_testlink_adaptor-0.33.dist-info/RECORD
