Metadata-Version: 2.1
Name: pytest-testlink-adaptor
Version: 0.33
Summary: pytest reporting plugin for testlink
Home-page: https://github.com/Blackwoodseller/pytest-testlink-adaptor/
Author: Blackwoodseller
Author-email: alpapot@gmail.com
License: MIT
Download-URL: https://github.com/Blackwoodseller/pytest-testlink-adaptor/tarball/0.33
Platform: any
Classifier: Environment :: Plugins
Classifier: Development Status :: 4 - Beta
Classifier: Intended Audience :: Developers
Classifier: License :: OSI Approved :: MIT License
Classifier: Operating System :: POSIX
Classifier: Operating System :: Microsoft :: Windows
Classifier: Operating System :: MacOS :: MacOS X
Classifier: Topic :: Software Development :: Testing
Classifier: Topic :: Software Development :: Libraries
Classifier: Topic :: Utilities
Classifier: Programming Language :: Python :: 2
Classifier: Programming Language :: Python :: 2.7
Classifier: Programming Language :: Python :: 3
Classifier: Programming Language :: Python :: 3.2
Classifier: Programming Language :: Python :: 3.3
Classifier: Programming Language :: Python :: 3.4
Classifier: Programming Language :: Python :: 3.5
Classifier: Programming Language :: Python :: 3.6
Classifier: Programming Language :: Python :: 3.7
Requires-Dist: pytest (>=2.6)
Requires-Dist: TestLink-API-Python-client
Requires-Dist: path.py
